lifelines/__init__.py
lifelines/calibration.py
lifelines/exceptions.py
lifelines/generate_datasets.py
lifelines/plotting.py
lifelines/statistics.py
lifelines/version.py
lifelines/datasets/CuZn-LeftCensoredDataset.csv
lifelines/datasets/__init__.py
lifelines/datasets/anderson.csv
lifelines/datasets/c_botulinum_lag_phase.csv
lifelines/datasets/canadian_senators.csv
lifelines/datasets/dd.csv
lifelines/datasets/dfcv_dataset.py
lifelines/datasets/divorce.dat
lifelines/datasets/g3.csv
lifelines/datasets/gbsg2.csv
lifelines/datasets/gehan.dat
lifelines/datasets/holly_molly_polly.tsv
lifelines/datasets/interval_diabetes.csv
lifelines/datasets/kidney_transplant.csv
lifelines/datasets/larynx.csv
lifelines/datasets/lung.csv
lifelines/datasets/lymph_node.csv
lifelines/datasets/lymphoma.csv
lifelines/datasets/merrell1955.csv
lifelines/datasets/mice.csv
lifelines/datasets/multicenter_aids_cohort.tsv
lifelines/datasets/nh4.csv
lifelines/datasets/panel_test.csv
lifelines/datasets/psychiatric_patients.csv
lifelines/datasets/recur.csv
lifelines/datasets/regression.csv
lifelines/datasets/rossi.csv
lifelines/datasets/stanford_heart.csv
lifelines/datasets/static_test.csv
lifelines/datasets/waltons_dataset.csv
lifelines/fitters/__init__.py
lifelines/fitters/aalen_additive_fitter.py
lifelines/fitters/aalen_johansen_fitter.py
lifelines/fitters/breslow_fleming_harrington_fitter.py
lifelines/fitters/cox_time_varying_fitter.py
lifelines/fitters/coxph_fitter.py
lifelines/fitters/crc_spline_fitter.py
lifelines/fitters/exponential_fitter.py
lifelines/fitters/generalized_gamma_fitter.py
lifelines/fitters/generalized_gamma_regression_fitter.py
lifelines/fitters/kaplan_meier_fitter.py
lifelines/fitters/log_logistic_aft_fitter.py
lifelines/fitters/log_logistic_fitter.py
lifelines/fitters/log_normal_aft_fitter.py
lifelines/fitters/log_normal_fitter.py
lifelines/fitters/mixins.py
lifelines/fitters/mixture_cure_fitter.py
lifelines/fitters/nelson_aalen_fitter.py
lifelines/fitters/npmle.py
lifelines-0.29.0.dist-info/LICENSE
lifelines-0.29.0.dist-info/METADATA
lifelines-0.29.0.dist-info/WHEEL
lifelines-0.29.0.dist-info/top_level.txt
lifelines-0.29.0.dist-info/RECORD
