Metadata-Version: 2.1
Name: lifelines
Version: 0.29.0
Summary: Survival analysis in Python, including Kaplan Meier, Nelson Aalen and regression
Home-page: https://github.com/CamDavidsonPilon/lifelines
Author: Cameron Davidson-Pilon
Author-email: cam.davidson.pilon@gmail.com
License: MIT
Classifier: Development Status :: 4 - Beta
Classifier: License :: OSI Approved :: MIT License
Classifier: Programming Language :: Python
Classifier: Programming Language :: Python :: 3.9
Classifier: Programming Language :: Python :: 3.10
Classifier: Programming Language :: Python :: 3.11
Classifier: Topic :: Scientific/Engineering
Requires-Python: >=3.9
License-File: LICENSE
Requires-Dist: numpy<2.0,>=1.14.0
Requires-Dist: scipy>=1.7.0
Requires-Dist: pandas>=2.1
Requires-Dist: matplotlib>=3.0
Requires-Dist: autograd>=1.5
Requires-Dist: autograd-gamma>=0.3
Requires-Dist: formulaic>=0.2.2
